[
    {
        "id": "2f534f5cdad606f7",
        "type": "delay",
        "z": "862f4876b87d50a6",
        "name": "",
        "pauseType": "delay",
        "timeout": "20",
        "timeoutUnits": "seconds",
        "rate": "1",
        "nbRateUnits": "1",
        "rateUnits": "second",
        "randomFirst": "1",
        "randomLast": "5",
        "randomUnits": "seconds",
        "drop": false,
        "allowrate": false,
        "outputs": 1,
        "x": 210,
        "y": 1060,
        "wires": [
            [
                "68a68984fbb3525b"
            ]
        ]
    }
]